{
  "parent": "l2backpack:backpacks/ender_drawer",
  "criteria": {
    "0": {
      "conditions": {
        "block": "l2backpack:ender_drawer"
      },
      "trigger": "minecraft:placed_block"
    }
  },
  "display": {
    "announce_to_chat": true,
    "description": {
      "translate": "advancements.l2backpack.advancements.backpacks.ender_drawer_place.description"
    },
    "frame": "goal",
    "hidden": false,
    "icon": {
      "item": "l2backpack:ender_drawer"
    },
    "show_toast": true,
    "title": {
      "translate": "advancements.l2backpack.advancements.backpacks.ender_drawer_place.title"
    }
  },
  "requirements": [
    [
      "0"
    ]
  ]
}